[
    {
        "exp_reward": 25,
        "gold_reward": 5,
        "item_rewards": null,
        "filename": null,
        "name": "Goblin",
        "hp": 20,
        "current_hp": 20,
        "mp": 0,
        "current_mp": 0,
        "attack": 6,
        "defense": 5,
        "speed": 5,
        "inventory": [],
        "skills": [],
        "level": 1,
        "experience": 0,
        "experience_to_level": 100,
        "total_experience": 0
    },
    {
        "exp_reward": 50,
        "gold_reward": 50,
        "item_rewards": null,
        "filename": null,
        "name": "Hob Goblin",
        "hp": 205,
        "current_hp": 205,
        "mp": 10,
        "current_mp": 10,
        "attack": 68,
        "defense": 82,
        "speed": 75,
        "inventory": [],
        "skills": [],
        "level": 1,
        "experience": 0,
        "experience_to_level": 100,
        "total_experience": 0
    },
    {
        "exp_reward": 75,
        "gold_reward": 100,
        "item_rewards": null,
        "filename": null,
        "name": "Lord Goblin",
        "hp": 305,
        "current_hp": 105,
        "mp": 70,
        "current_mp": 70,
        "attack": 160,
        "defense": 150,
        "speed": 150,
        "inventory": [],
        "skills": [],
        "level": 1,
        "experience": 0,
        "experience_to_level": 100,
        "total_experience": 0
    },
    {
        "exp_reward": 100,
        "gold_reward": 500,
        "item_rewards": null,
        "filename": null,
        "name": "King Goblin",
        "hp": 780,
        "current_hp": 580,
        "mp": 300,
        "current_mp": 300,
        "attack": 90,
        "defense": 80,
        "speed": 80,
        "inventory": [],
        "skills": [],
        "level": 1,
        "experience": 0,
        "experience_to_level": 100,
        "total_experience": 0
    }
]